pyfacebook/__init__.py
pyfacebook/api/__init__.py
pyfacebook/api/base_client.py
pyfacebook/api/base_resource.py
pyfacebook/api/facebook/__init__.py
pyfacebook/api/facebook/client.py
pyfacebook/api/facebook/common_edges/__init__.py
pyfacebook/api/facebook/common_edges/albums.py
pyfacebook/api/facebook/common_edges/comments.py
pyfacebook/api/facebook/common_edges/feed.py
pyfacebook/api/facebook/common_edges/likes.py
pyfacebook/api/facebook/common_edges/live_videos.py
pyfacebook/api/facebook/common_edges/photos.py
pyfacebook/api/facebook/common_edges/videos.py
pyfacebook/api/facebook/resource/__init__.py
pyfacebook/api/facebook/resource/album.py
pyfacebook/api/facebook/resource/application.py
pyfacebook/api/facebook/resource/business.py
pyfacebook/api/facebook/resource/comment.py
pyfacebook/api/facebook/resource/conversation.py
pyfacebook/api/facebook/resource/event.py
pyfacebook/api/facebook/resource/group.py
pyfacebook/api/facebook/resource/live_video.py
pyfacebook/api/facebook/resource/message.py
pyfacebook/api/facebook/resource/page.py
pyfacebook/api/facebook/resource/photo.py
pyfacebook/api/facebook/resource/post.py
pyfacebook/api/facebook/resource/user.py
pyfacebook/api/facebook/resource/video.py
pyfacebook/api/graph.py
pyfacebook/api/instagram_basic/__init__.py
pyfacebook/api/instagram_basic/client.py
pyfacebook/api/instagram_basic/resource/__init__.py
pyfacebook/api/instagram_basic/resource/media.py
pyfacebook/api/instagram_basic/resource/user.py
pyfacebook/api/instagram_business/__init__.py
pyfacebook/api/instagram_business/client.py
pyfacebook/api/instagram_business/resource/__init__.py
pyfacebook/api/instagram_business/resource/comment.py
pyfacebook/api/instagram_business/resource/container.py
pyfacebook/api/instagram_business/resource/hashtag.py
pyfacebook/api/instagram_business/resource/media.py
pyfacebook/api/instagram_business/resource/user.py
pyfacebook/exceptions.py
pyfacebook/models/__init__.py
pyfacebook/models/album.py
python_facebook_api-0.20.0.dist-info/LICENSE
python_facebook_api-0.20.0.dist-info/METADATA
python_facebook_api-0.20.0.dist-info/WHEEL
python_facebook_api-0.20.0.dist-info/RECORD
