Metadata-Version: 2.1
Name: python-facebook-api
Version: 0.20.0
Summary: A simple Python wrapper around the Facebook Graph API
Home-page: https://github.com/sns-sdks/python-facebook
License: Apache-2.0
Keywords: facebook-graph-api,facebook-sdk,instagram-api,instagram-sdk,facebook-api
Author: Ikaros kun
Author-email: merle.liukun@gmail.com
Requires-Python: >=3.7,<4.0
Classifier: License :: OSI Approved :: Apache Software License
Classifier: Operating System :: OS Independent
Classifier: Programming Language :: Python
Classifier: Programming Language :: Python :: 3
Classifier: Programming Language :: Python :: 3.7
Classifier: Programming Language :: Python :: 3.8
Classifier: Programming Language :: Python :: 3.9
Classifier: Programming Language :: Python :: 3.10
Classifier: Programming Language :: Python :: 3.11
Classifier: Programming Language :: Python :: 3.12
Classifier: Programming Language :: Python :: 3 :: Only
Classifier: Topic :: Software Development :: Libraries
Requires-Dist: dataclasses-json (>=0.5.7)
Requires-Dist: requests (>=2.27,<3.0)
Requires-Dist: requests-oauthlib (>=1.2.0,<2.0.0)
Project-URL: Repository, https://github.com/sns-sdks/python-facebook
